ldstore/__init__.py
ldstore/bcor.py
ldstore/bdose.py
ldstore/parse.py
ldstore-0.1.9.data/data/LICENSE
ldstore-0.1.9.dist-info/LICENSE
ldstore-0.1.9.dist-info/METADATA
ldstore-0.1.9.dist-info/WHEEL
ldstore-0.1.9.dist-info/top_level.txt
ldstore-0.1.9.dist-info/RECORD
