Metadata-Version: 2.1
Name: ldstore
Version: 0.1.9
Summary: A package for reading files created by LDstore
Home-page: http://www.finemap.me
Author: Christian Benner
Author-email: christian.benner@helsinki.fi
License: UNKNOWN
Platform: UNKNOWN
Classifier: Programming Language :: Python :: 3
Classifier: License :: OSI Approved :: MIT License
Classifier: Operating System :: OS Independent
Requires-Python: >= 3.8
Requires-Dist: numpy
Requires-Dist: pandas
Requires-Dist: zstd
